fast_plaid/fast_plaid_rust.cp313-win_amd64.pyd
fast_plaid/__init__.py
fast_plaid/evaluation/evaluation.py
fast_plaid/evaluation/__init__.py
fast_plaid/filtering/filtering.py
fast_plaid/filtering/__init__.py
fast_plaid/search/fast_plaid.py
fast_plaid/search/kmeans.py
fast_plaid/search/load.py
fast_plaid/search/profile.py
fast_plaid/search/update.py
fast_plaid/search/__init__.py
fast_plaid-1.4.2.290.dist-info/DELVEWHEEL
fast_plaid-1.4.2.290.dist-info/METADATA
fast_plaid-1.4.2.290.dist-info/RECORD
fast_plaid-1.4.2.290.dist-info/WHEEL
fast_plaid-1.4.2.290.dist-info/licenses/LICENSE
fast_plaid.libs/c10-8edffc4d3f604bc796603a6c06aab48b.dll
fast_plaid.libs/msvcp140-a4c2229bdc2a2a630acdc095b4d86008.dll
